odoo/addons/test_ssi_mixin/README.rst
odoo/addons/test_ssi_mixin/__init__.py
odoo/addons/test_ssi_mixin/__manifest__.py
odoo/addons/test_ssi_mixin/menu.xml
odoo/addons/test_ssi_mixin/data/dev_model_type_data.xml
odoo/addons/test_ssi_mixin/models/__init__.py
odoo/addons/test_ssi_mixin/models/dev_model_type.py
odoo/addons/test_ssi_mixin/security/ir.model.access.csv
odoo/addons/test_ssi_mixin/static/description/icon.png
odoo/addons/test_ssi_mixin/static/description/index.html
odoo/addons/test_ssi_mixin/static/img/bug.png
odoo/addons/test_ssi_mixin/static/img/circuit.png
odoo/addons/test_ssi_mixin/static/img/download.png
odoo/addons/test_ssi_mixin/static/img/info.png
odoo/addons/test_ssi_mixin/static/img/medal.png
odoo/addons/test_ssi_mixin/static/img/questions.png
odoo/addons/test_ssi_mixin/static/img/workflow.png
odoo/addons/test_ssi_mixin/views/dev_model_type_view.xml
odoo_addon_test_ssi_mixin-18.0.1.0.2.2.dist-info/METADATA
odoo_addon_test_ssi_mixin-18.0.1.0.2.2.dist-info/WHEEL
odoo_addon_test_ssi_mixin-18.0.1.0.2.2.dist-info/top_level.txt
odoo_addon_test_ssi_mixin-18.0.1.0.2.2.dist-info/RECORD
